Workbook
Name ConditionID: #REF!
Name ShippingPolicyNameFunction: BusinessPolicy!$A$2:$A$6
Name ReturnPolicyNameFunction: BusinessPolicy!$B$2:$B$2
Name PaymentPolicyNameFunction: BusinessPolicy!$C$2:$C$2
Name _170080_CId: Categories!$C$2:$J$2
Name CategoryIdNameFunction: Categories!$B$2:$B$2
Name CategoryNameNameFunction: Categories!$A$2:$A$2
Name _170080_CBrand: Aspects!F3:AIC3
Name _170080_CType: Aspects!F4:S4
Name _170080_CCompatibleMotherboardBrand: Aspects!F5:AD5
Name _170080_CUnitType: Aspects!F8:M8
Name _170080_CCountryofOrigin: Aspects!F9:IO9
Name _170080_CManufacturerWarranty: Aspects!F14:P14

Sheet GENERAL INSTRUCTIONS
B1: GENERAL INSTRUCTIONS
B2: Getting started: In order to start using Seller Hub Reports, we recommend you start by listing 1 or 2 items on eBay to help you understand listings. On the template file, start from left to right using the Add action to add new listings and fill in each column; some will have dropdown menus to select from as well as tool tip notes on each column header. It's important to fill in color coded item specifics. These item specifics will help buyers narrow down their search results to find your listings. Variations: When you want to list many similar items that have different variables, such as color or size, you can create listings that include all the variations you offer. For creating a listing with variations there will be a parent-child relationship for the following fields: Relationship, RelationshipDetails, P:UPC, StartPrice, Quantity and PicURL and CustomLabel(optionally). Parent row: The first row should only contain the normal listing information, like Action, Category, Format, and other shared information (like shipping and returns options) that apply to all the variations in the listing. Do not add any of this information to your child rows. The exception to this would be that all of your variables would be added to the parent row for RelationshipDetails such as: Color=Red;Blue| Size=Small,Medium. Child row: Child rows begin directly underneath each parent row in the Relationship column and each child row will contain one variable set from your named variations. Also information on your child rows will be added to P:UPC, Start Price, Quantity and optionally, Custom Label (SKU) and Item photo URL.
B4: Table 1.0
B5: *Action(SiteID=US|Country=US|Currency=USD|Version=941) | C5: Category ID | D5: Custom Label (SKU) | E5: Relationship | F5: Relationship details | G5: P:UPC | H5: Quantity | I5: Start Price | J5: Item photo URL. | K5: P:EAN | L5: P:EPID | N5: Subtitle
A6: Parent row | B6: Add | C6: 260955 | D6: Men-shirts | F6: Color=Red;Blue|Size=Small;Medium | J6: https://www.picturshosting site.com/picturefolder/picturename1.jpg
A7: child row | D7: Red-S | E7: Variation | F7: Color=Red|Size=Small | G7: 097361197548 | H7: 3 | I7: 5 | J7: Red=https://www.picturshosting site.com/picturefolder/picturename8.jpg
A8: child row | D8: Red-M | E8: Variation | F8: Color=Red|Size=Medium | G8: 97361197549 | H8: 3 | I8: 6 | J8: Blue=https://www.picturshosting site.com/picturefolder/picturename3.jpg
A9: child row | D9: Blue-M | E9: Variation | F9: Color=Blue|Size=Medium | G9: 97361197560 | H9: 3 | I9: 6
A10: child row | D10: Blue-S | E10: Variation | F10: Color=Blue|Size=Small | G10: 97361197590 | H10: 4 | I10: 5
B12: IMPORTANT
B13: 1. Photos need to be provided in the file template via links to the web-hosted images. The photo URL needs to start with the hypertext https:// and end with a file extension like .jpg or .png. eBay recommends - a minimum of 500 pixels on the longest side, 800 pixels on the longest side to zoom on the listing page. 1200 pixels is optimal. 2. Pipe character | - You can add up to 12 photos on the parents row and each variation row. When doing so, use the pipe ( | ) character to separate the values https://www.picturshosting site.com/picturefolder/picturename1.jpg|https://www.picturshosting site.com/picturefolder/picturename3.jpg
B18: Fill out missing fields on a template
C19: Indicates missing required field for a listing | G19: 1. Hover your mouse over headers to see column header definitions.
C20: Indicates missing field that will be required soon | G20: 2. Click on the cell with missing fields.
C21: Indicates missing recommended field for a listing | G21: 3. Click on the arrow that appears beside the cell.
C22: Indicates field does not apply to this item/category | G22: 4. Select an applicable value from the list or enter a custom value.
B25: Setting up Shipping, Payments & Returns
B26: If you opted into Business Policies on your Seller account page, the following fields should not be used on this template:
B27: Payments
B28: Paypal accepted, Paypal email address, Immediate pay required, Payment instructions.
B29: Shipping
B30: Shipping service 1 option, Shipping service 1 cost, Shipping service 1 priority, Shipping service 2 option, Shipping service 2 cost, Shipping service 2 priority, Max dispatch time.
B31: Returns
B32: Returns accepted option, Returns within option, Refund option, Return shipping cost paid by.
B34: Instead, use these fields: Shipping profile name, Return profile name, Payment profile name.
B35: https://www.ebay.com/bp/manage
B37: Schedule time
B38: Schedule Time field can be used to schedule a listing to start at a specific time in the future (listings cannot be started in the past).
... B45: https://pages.ebay.com/sh/reports/help/create-listings-bulk/#_nq6onyvjkyg

Sheet Listings
A1: #INFO | B1: Created=1768262583898 | G1: Indicates missing required fields | L1: Indicates missing field that will be required soon
A2: #INFO | B2: Version=1.0 | D2: Template=fx_category_template_EBAY_US | G2: Indicates missing recommended field | L2: Indicates field does not apply to this item/category
A3: #INFO
A4: *Action(SiteID=US|Country=US|Currency=USD|Version=1193) | B4: Custom label (SKU) | C4: Category ID | D4: Category name | E4: Title | F4: Relationship | G4: Relationship details | H4: Schedule Time | I4: P:UPC | J4: P:EPID | K4: Start price | L4: Quantity | M4: Item photo URL | N4: VideoID | O4: Condition ID | P4: Description | Q4: Format | R4: Duration | S4: Buy It Now price | T4: Best Offer Enabled | U4: Best Offer Auto Accept Price | V4: Minimum Best Offer Price | W4: Immediate pay required | X4: Location | Y4: Shipping service 1 option | Z4: Shipping service 1 cost | AA4: Shipping service 1 priority | AB4: Shipping service 2 option | AC4: Shipping service 2 cost | AD4: Shipping service 2 priority | AE4: Max dispatch time | AF4: Returns accepted option | AG4: Returns within option | AH4: Refund option | AI4: Return shipping cost paid by | AJ4: Shipping profile name | AK4: Return profile name | AL4: Payment profile name | AM4: TakeBackPolicyID | AN4: Regional TakeBackPolicies | AO4: EcoParticipationFee | AP4: C:Brand | AQ4: C:Type | AR4: C:Compatible Motherboard Brand | AS4: C:MPN | AT4: C:Unit Quantity | AU4: C:Unit Type | AV4: Product Safety Pictograms | AW4: Product Safety Statements | AX4: Product Safety Component | AY4: Regulatory Document Ids | AZ4: Manufacturer Name | BA4: Manufacturer AddressLine1 | BB4: Manufacturer AddressLine2 | BC4: Manufacturer City | BD4: Manufacturer Country | BE4: Manufacturer PostalCode | BF4: Manufacturer StateOrProvince | BG4: Manufacturer Phone | BH4: Manufacturer Email | BI4: Manufacturer ContactURL | BJ4: Responsible Person 1 | BK4: Responsible Person 1 Type | BL4: Responsible Person 1 AddressLine1 | BM4: Responsible Person 1 AddressLine2 | BN4: Responsible Person 1 City | BO4: Responsible Person 1 Country | BP4: Responsible Person 1 PostalCode | BQ4: Responsible Person 1 StateOrProvince | BR4: Responsible Person 1 Phone | BS4: Responsible Person 1 Email | BT4: Responsible Person 1 ContactURL
C5: =IF(NOT(ISBLANK(D5)), VLOOKUP(D5,Categories!$A$2:$B$51,2,FALSE), "") -> 0
C6: =IF(NOT(ISBLANK(D6)), VLOOKUP(D6,Categories!$A$2:$B$51,2,FALSE), "") -> 0
C7: =IF(NOT(ISBLANK(D7)), VLOOKUP(D7,Categories!$A$2:$B$51,2,FALSE), "") -> 0
C8: =IF(NOT(ISBLANK(D8)), VLOOKUP(D8,Categories!$A$2:$B$51,2,FALSE), "") -> 0
C9: =IF(NOT(ISBLANK(D9)), VLOOKUP(D9,Categories!$A$2:$B$51,2,FALSE), "") -> 0
C10: =IF(NOT(ISBLANK(D10)), VLOOKUP(D10,Categories!$A$2:$B$51,2,FALSE), "") -> 0
C11: =IF(NOT(ISBLANK(D11)), VLOOKUP(D11,Categories!$A$2:$B$51,2,FALSE), "") -> 0
C12: =IF(NOT(ISBLANK(D12)), VLOOKUP(D12,Categories!$A$2:$B$51,2,FALSE), "") -> 0
C13: =IF(NOT(ISBLANK(D13)), VLOOKUP(D13,Categories!$A$2:$B$51,2,FALSE), "") -> 0
C14: =IF(NOT(ISBLANK(D14)), VLOOKUP(D14,Categories!$A$2:$B$51,2,FALSE), "") -> 0
C15: =IF(NOT(ISBLANK(D15)), VLOOKUP(D15,Categories!$A$2:$B$51,2,FALSE), "") -> 0
C16: =IF(NOT(ISBLANK(D16)), VLOOKUP(D16,Categories!$A$2:$B$51,2,FALSE), "") -> 0
... C100000: =IF(NOT(ISBLANK(D100000)), VLOOKUP(D100000,Categories!$A$2:$B$51,2,FALSE), "") -> 0

Sheet Categories
A1: Category Name | B1: Category ID
A2: /Computers/Tablets & Networking/Computer Components & Parts/Motherboard Components & Accs/Motherboard Backplates | B2: 170080 | C2: 7000-For parts or not working | D2: 1500-Open box | E2: 1000-New | F2: 2000-Certified - Refurbished | G2: 2010-Excellent - Refurbished | H2: 3000-Used | I2: 2020-Very Good - Refurbished | J2: 2030-Good - Refurbished

Sheet ListingStaticData
A1: Header | B1: Mandatory | C1: Values
A4: Action | B4: 1 | C4: Add
A5: Relationship | C5: Variation | D5: Compatibility
A6: Format | C6: Auction | D6: FixedPrice
A7: Return shipping cost paid by | C7: Buyer | D7: Seller
A8: Duration | C8: 1 | D8: 3 | E8: 5 | F8: 7 | G8: 10 | H8: GTC
A9: Responsible Person 1 Type | C9: EUResponsiblePerson

Sheet BusinessPolicy
A1: ShippingPolicyNames | B1: ReturnPolicyNames | C1: PaymentPolicyNames
A2: Medium Box - (ID: 238525632025) | B2: muoi bon ngay money back or replacement - (ID: 235542853025) | C2: Default Payment - (ID: 235542855025)
A3: Calculated shipping, competitive pricing (IO 4 pieces) - (ID: 238373217025)
A4: FREE shipping - (ID: 245390257025)
A5: IO Shipping Costly - (ID: 235542854025)
A6: Tiny Cheap Items - (ID: 235542856025)

Sheet Aspects
B2: AspectName | C2: FunctionName | D2: CategoryAspectCombined | E2: Level | F2: Values
A3: 170080 | B3: C:Brand | C3: CBrand | D3: 170080C:Brand | E3: REQUIRED | F3: Unbranded | G3: 2Wire | H3: 3Com | I3: 3Dconnexion | J3: 3dfx | K3: 3DLABS | L3: 3M | M3: 3P | N3: 3ware | O3: 4XEM | P3: a/d/s/ | Q3: A.E.S | R3: Aastra | S3: Ability | T3: Abit | U3: ABS Computer Technologies | V3: AB Soft | W3: ACARD Technology | X3: ACE | Y3: Acer | Z3: ACI | AA3: Acomdata | AB3: Acorn | AC3: Acoustic Research | AD3: Acronis | AE3: ACS | AF3: Action-Tec | AG3: Adaptec | AH3: ADATA | AI3: Addlogix | AJ3: AddOn | AK3: Addonics | AL3: Adesso | AM3: Adic | AN3: ADI Corporation | AO3: Adobe Systems | AP3: ADTRAN | AQ3: Advantech | AR3: Advent | AS3: AeroCool | AT3: Afga | AU3: Afreey | AV3: Agfa | AW3: AG Neovo | AX3: Airlink | AY3: Akasa | AZ3: Albatron | BA3: Alcatel | BB3: Alcatel-Lucent | BC3: Alera Technologies | BD3: Alienware | BE3: Allied telesyn | BF3: Allume Systems | BG3: Alpha | BH3: Alphacool | BI3: Alps | BJ3: Altos | BK3: Aluratek | BL3: Amacom | BM3: Ambir | BN3: AMD | BO3: American Anko | BP3: AMP | BQ3: AMS | BR3: Amstrad | BS3: Antec | BT3: AOPEN | BU3: Apacer | BV3: APC | BW3: Apple | BX3: Apricot | BY3: Archive | BZ3: Archos | CA3: ArcSoft | CB3: Arctic Cooling | CC3: Arctic Silver | CD3: Arduino | CE3: Areca | CF3: Argosy | CG3: Aries | CH3: Artec | CI3: Artronix Technology | CJ3: Asetek | CK3: Ashampoo | CL3: Asound | CM3: Aspire Digital | CN3: ASRock | CO3: AST | CP3: ASTEC | CQ3: AST Research Inc. | CR3: ASUS | CS3: AT&T | CT3: Atari | CU3: ATEN | CV3: ATI | CW3: ATL Telecom | CX3: ATMT | CY3: ATP Electronic | CZ3: ATTO | DA3: Audigy | DB3: AUDIOTRAK | DC3: Auralog | DD3: Aurora Electronics | DE3: Autodesk | DF3: Avanquest | DG3: Avaya | DH3: Averatec | DI3: AVerMedia | DJ3: Avery | DK3: AVG | DL3: Avid | DM3: Avision | DN3: Axis | DO3: AzenX | DP3: Aztech | DQ3: Bauer Vehicle Gear | DR3: BayTech | DS3: Behringer | DT3: Belkin | DU3: Bell and Howell | DV3: Benchmark | DW3: BenQ | DX3: Bestec | DY3: BFG | DZ3: Big Print | EA3: Billionton | EB3: BIOSTAR | EC3: BitDefender | ED3: BitFenix | EE3: Black Box | EF3: Bondwell | EG3: Borland | EH3: Boundless Technology | EI3: Brand-Rex | EJ3: Bretford | EK3: Brocade | EL3: Brother | EM3: BTC | EN3: Buffalo | EO3: Buffalo Technology | EP3: Burroughs | EQ3: Busbi | ER3: Business Objects | ES3: BUSlink | ET3: Bytestor | EU3: C2G | EV3: Cable & Wireless | EW3: Canon | EX3: Canopus | EY3: CASECOM | EZ3: Casio | FA3: Cavalry | FB3: Centon | FC3: Ceratech | FD3: Certance | FE3: CGL | FF3: CHIMEI | FG3: Chronos | FH3: Chunghwa Telecom | FI3: Ciprico | FJ3: Cirrus Logic | FK3: Cisco | FL3: CiT | FM3: Citizen | FN3: CLEVO | FO3: Club 3D | FP3: C-media | FQ3: CMS | FR3: Cobra | FS3: Codegen | FT3: ColecoVision | FU3: Colourado | FV3: Comlynx | FW3: Commodore | FX3: Compaq | FY3: Compucase | FZ3: Compucessory | GA3: Computer Associates | GB3: Computers by Design | GC3: Comsol | GD3: Conceptronic | GE3: Condre | GF3: Conexant Systems | GG3: CONITECH | GH3: Connect3d | GI3: Conrad | GJ3: Convergent Technologies | GK3: Cooler Master | GL3: COOLMAX | GM3: Copystar | GN3: Corega | GO3: Corel | GP3: Corsair | GQ3: CPUBuilders | GR3: Cradlepoint | GS3: Creative | GT3: Cristie Electronics | GU3: Crucial | GV3: CTX | GW3: Custom, Whitebox | GX3: Cyber Acoustics | GY3: CyberDrive | GZ3: CyberLink | HA3: Cybernet | HB3: CyberPower | HC3: CybertronPC | HD3: Cyclone | HE3: Cyrix | HF3: DabsValue | HG3: Da-Lite | HH3: Dane-Elec | HI3: Datamax-ONeil | HJ3: Datawrite | HK3: Dazzle | HL3: DEC | HM3: Delkin | HN3: Dell | HO3: Delta | HP3: DFI | HQ3: Diamond Multimedia | HR3: DICOTA | HS3: Digi | HT3: Digicom | HU3: Digiflex | HV3: Digimate | HW3: Digital Audio Labs | HX3: Digital Innovations | HY3: Digital Memory | HZ3: Digital Research | IA3: DIKOM | IB3: Disgo | IC3: Disney | ID3: D-Link | IE3: Double-H Boots | IF3: DPI | IG3: Dragon | IH3: DrayTek | II3: Drobo | IJ3: Dual Electronics | IK3: DViCO | IL3: Dymo | IM3: Dynamode | IN3: Dynatron | IO3: Dynex | IP3: EasyCap | IQ3: Ebuyer | IR3: Ecrix | IS3: ECS | IT3: EDGE Tech Corp | IU3: EDIMAX | IV3: Edirol | IW3: EIZO | IX3: eJay | IY3: Elettrodata | IZ3: Elgato | JA3: Elitegroup | JB3: Elixir | JC3: Elo | JD3: Elo Touch Solutions | JE3: ELSA | JF3: Eltron | JG3: eMachines | JH3: Emagic | JI3: EMC | JJ3: Emerson | JK3: Empire | JL3: Emprex | JM3: Emtec | JN3: Emtec Magnetics Group | JO3: E-MU | JP3: Encore Electronics | JQ3: Encyclopaedia Britannica | JR3: Enermax | JS3: EnGenius | JT3: Engineering Software | JU3: Enlight | JV3: Enzotech | JW3: Epcbuyer | JX3: Epiq Systems | JY3: EP Memory | JZ3: EPoX | KA3: Epson | KB3: Ergo | KC3: EuroTalk | KD3: EVERCOOL | KE3: Everex | KF3: Evergreen Solar | KG3: Evesham | KH3: EVGA | KI3: Exabyte | KJ3: Executive Software | KK3: Exide | KL3: EXPANSYS | KM3: Extensis | KN3: Extreme | KO3: Extreme Networks | KP3: EZPnP | KQ3: EZQuest | KR3: Fantom Drives | KS3: Fargo | KT3: Fellowes | KU3: FIC | KV3: FileMaker | KW3: Fire-Lite | KX3: FirewireDirect | KY3: Fluke Networks | KZ3: Focus Enhancements | LA3: Focus Multimedia | LB3: Focusrite | LC3: Formac | LD3: FortiVoice | LE3: Fostex | LF3: Foxconn | LG3: Fractal Design | LH3: Freecom | LI3: Frontier | LJ3: FSC | LK3: F-Secure | LL3: FSP | LM3: Fuji | LN3: Fujifilm | LO3: Fujitsu | LP3: Fujitsu Siemens | LQ3: Fusion | LR3: Gainward | LS3: Garmin | LT3: Gateway | LU3: Gecube | LV3: GELID Solutions | LW3: Generic Memory | LX3: Genius | LY3: GERICOM | LZ3: Getac | MA3: GIGABYTE | MB3: GigaPlus | MC3: GIGATAIN | MD3: Global Marketing Partners | ME3: Glyph | MF3: Golden Emperor | MG3: GoldenRAM | MH3: Goldstar | MI3: Grad | MJ3: Grandstream | MK3: Greenstreet Software | ML3: Griffin | MM3: Grundig | MN3: Grundy | MO3: GS Magicstor | MP3: Guillemot | MQ3: GVC | MR3: H.I.S | MS3: HABEY | MT3: Hama | MU3: Ham-Let | MV3: Handspring | MW3: Hannspree | MX3: Hauppauge | MY3: Hawking | MZ3: Hercules | NA3: Highpoint Technologies | NB3: HiPer | NC3: Hitachi | ND3: Hi-Val | NE3: Honest Technology | NF3: Honeywell | NG3: Howard Technology Solutions | NH3: HP | NI3: HT Enterprises | NJ3: Hurricane | NK3: Hynix | NL3: Hypertec | NM3: Hyundai | NN3: IBM | NO3: IceBox | NP3: ICY BOX | NQ3: IEI | NR3: iiyama | NS3: ILY Enterprise | NT3: Imation | NU3: I-Modetech | NV3: iMount | NW3: Impression Products | NX3: IMSI | NY3: Individual Software | NZ3: Infineon | OA3: InFocus | OB3: Ingram | OC3: Innolux | OD3: Innovation Cooling | OE3: Innovation First | OF3: Insignia | OG3: Inspiration | OH3: Integral | OI3: Intel | OJ3: Intellinet | OK3: Intellivision | OL3: Intermec | OM3: Intreeo | ON3: Intuit | OO3: Intuix | OP3: IOCell | OQ3: I-O DATA DEVICE, INC. | OR3: IOGEAR | OS3: iolo | OT3: Iomega | OU3: Iridium | OV3: IRIS | OW3: Irradio | OX3: iSTAR | OY3: iStarUSA | OZ3: ITOCHU | PA3: Itronix | PB3: I will | PC3: Ixix | PD3: IXOS | PE3: Javelin Systems | PF3: JayTech | PG3: JET | PH3: Jetway | PI3: JMTek | PJ3: Jungsoft | PK3: Juniper Networks | PL3: Jupiter Ace | PM3: JVC | PN3: KAOS Systems | PO3: Kaypro | PP3: Kensington | PQ3: KINGMAX | PR3: Kingston | PS3: Kingwin | PT3: Kodak | PU3: Konica Minolta | PV3: Konig | PW3: Koutech Systems, Inc | PX3: KWorld | PY3: Kyocera | PZ3: Labtec | QA3: LaCie | QB3: Laird | QC3: Laser | QD3: Lavasoft | QE3: L-com | QF3: Leadtek | QG3: Lenovo | QH3: LevelOne | QI3: Leviton | QJ3: Lexicon | QK3: Lexmark | QL3: LG | QM3: LG Display | QN3: Lian Li | QO3: LifeView | QP3: LightScribe | QQ3: Line 6 | QR3: Link Depot | QS3: LINKIT | QT3: Linksys | QU3: Linkworld Electronic Co. | QV3: Linspire | QW3: Lite-On | QX3: Logickeyboard | QY3: Logik | QZ3: Logisys | RA3: Logitech | RB3: Lotus | RC3: Lowe | RD3: LSI | RE3: Lucent | RF3: L X É | RG3: Macally | RH3: Maco | RI3: Macromedia | RJ3: Magic | RK3: MAG Innovision | RL3: MAGIX | RM3: Magnex | RN3: Manhattan | RO3: Marconi | RP3: Margi | RQ3: MASSCOOL | RR3: Matrix | RS3: Matrix Games | RT3: Matrox | RU3: Mattel | RV3: M-Audio | RW3: MAXDATA | RX3: Maxell | RY3: MaxOptic | RZ3: Maxspeed | SA3: Maxtor | SB3: Maxwell | SC3: McAfee | SD3: MCM | SE3: MediaCom | SF3: MediaFORM | SG3: Media Go | SH3: Medialink | SI3: MEDION | SJ3: Memorex | SK3: Memup | SL3: Meritline | SM3: Mesh | SN3: MGE | SO3: Microboards | SP3: Micro Direct | SQ3: Micro Electronics | SR3: Micron | SS3: Microsoft | ST3: Micro Solutions | SU3: Microstar | SV3: Microtek | SW3: Microtel | SX3: Miglia | SY3: Miglia Technology | SZ3: MikroTik | TA3: Minolta | TB3: Mirai | TC3: MiTAC | TD3: Mitsubishi | TE3: Mitsumi | TF3: Moby Memory | TG3: Molex | TH3: Monarch Specialties | TI3: Monorail | TJ3: Monster | TK3: Motion | TL3: Motorola | TM3: MPC Computers | TN3: MPIO | TO3: MSI | TP3: MST Cables | TQ3: MSX | TR3: Multi-Code | TS3: Mushkin Enhanced | TT3: Musiland | TU3: Mustek | TV3: Mutoh | TW3: MyGica | TX3: NCR | TY3: NEC | TZ3: NEON | UA3: NetApp | UB3: NetComm | UC3: NETGEAR | UD3: Net Nanny | UE3: Netopia | UF3: Network Associates | UG3: New Balance | UH3: New Media | UI3: NEXT | UJ3: Nexus | UK3: Nikon | UL3: Nintendo | UM3: Nippon | UN3: Nisis | UO3: Noctua | UP3: Norcent Technologies | UQ3: Nortech | UR3: Nortel | US3: Northgate | UT3: NovAtel | UU3: nSpire | UV3: NTI | UW3: Nuance | UX3: Number Nine | UY3: Nutech Aluminum Products | UZ3: NVIDIA | VA3: NZXT | VB3: O'Dixion | VC3: OAK | VD3: OCZ | VE3: Odys | VF3: OEM Systems | VG3: OKGEAR | VH3: OKI | VI3: OKIA | VJ3: Olivetti | VK3: Olympus | VL3: OnStream | VM3: opiumex | VN3: Optorite | VO3: Optronix | VP3: OQO | VQ3: Orange | VR3: ORIC | VS3: Origin Storage | VT3: Orion | VU3: Orlogix | VV3: Ortronics | VW3: Otium | VX3: Overland Data | VY3: Overland Storage | VZ3: OWC | WA3: Pace | WB3: Pacific Digital | WC3: Packard Bell | WD3: Palit | WE3: Palm | WF3: Panasonic | WG3: Pandigital | WH3: Paradigm | WI3: Partner Tech | WJ3: Patriot | WK3: PDP Systems, Inc | WL3: Peavey | WM3: Pelham Sloane | WN3: PenDrive | WO3: Pengo | WP3: Peplink | WQ3: Performance Technology | WR3: Philips | WS3: PikaOne | WT3: PINE Technology | WU3: Pinnacle | WV3: Pinnacle Systems | WW3: PioData | WX3: Pioneer | WY3: PioneerPOS | WZ3: PixelView | XA3: PIXMANIA | XB3: Planar | XC3: Planet Technology | XD3: Plantronics | XE3: Plasmon | XF3: Platinum | XG3: PLEXTOR | XH3: Plexus | XI3: Plustek | XJ3: PNY | XK3: Point of Sale | XL3: Point of View | XM3: Polycom | XN3: Polywell | XO3: Porsche | XP3: Portable Addons | XQ3: Port Incorporated | XR3: Posiflex | XS3: POS-X | XT3: Power Brake Sales | XU3: PowerColor | XV3: PowerFile | XW3: Powervar | XX3: Powerware | XY3: POWMAX | XZ3: PQI | YA3: PreSonus | YB3: PreTec | YC3: Prime | YD3: PrimeArray | YE3: Primera | YF3: Primera Technology, Inc. | YG3: Printronix | YH3: Prism | YI3: Procom | YJ3: Prolimatech Inc. | YK3: Protégé | YL3: Proxim | YM3: Psion | YN3: PTC | YO3: Puget Systems | YP3: QLTY | YQ3: QPS | YR3: Qualcomm | YS3: QUANTA | YT3: Quantum | YU3: Quark | YV3: Quatech | YW3: Quest | YX3: Quicken | YY3: Racer | YZ3: Raidmax | ZA3: Ratoc Systems | ZB3: RCA | ZC3: Realtek | ZD3: RedJag | ZE3: reflecta | ZF3: Relisys | ZG3: ReTrak | ZH3: Rexus | ZI3: RicaVision | ZJ3: Ricoh | ZK3: Rimage | ZL3: Rio | ZM3: Riverstone Networks | ZN3: Robotron | ZO3: Rocstor | ZP3: Roland | ZQ3: Rollei | ZR3: Rosewill | ZS3: Roxio | ZT3: Rugged Notebooks | ZU3: Sabrent | ZV3: Safco | ZW3: SafeCom | ZX3: Sagem | ZY3: Sager | ZZ3: Sage Software | AAA3: SainSmart | AAB3: Samsung | AAC3: Sandberg | AAD3: SanDisk | AAE3: Santak | AAF3: SANYO | AAG3: Sapido | AAH3: SAPPHIRE | AAI3: Sava Value | AAJ3: Schaub Lorenz | AAK3: Schneider | AAL3: Scythe | AAM3: Seagate | AAN3: Sea Sonic | AAO3: SEGA | AAP3: Seiko | AAQ3: Serif | AAR3: SGI | AAS3: Sharkoon | AAT3: Sharp | AAU3: Shecom Computers | AAV3: Shintaro | AAW3: Shuttle | AAX3: Siemens | AAY3: Sierra Wireless | AAZ3: Signature | ABA3: SIIG | ABB3: Silex | ABC3: Silverstone | ABD3: SimpleTech | ABE3: Sinclair | ABF3: Sintech | ABG3: SIS | ABH3: Sitecom | ABI3: SkipDr | ABJ3: Smart | ABK3: SmartDisk | ABL3: SmartMedia | ABM3: SMART Modular Technologies | ABN3: SMC | ABO3: Smith & Wesson | ABP3: Socket Communications | ABQ3: SolidTEk | ABR3: Sonnet | ABS3: Sony | ABT3: Soyo | ABU3: SparkFun | ABV3: Sparkle Power Inc. | ABW3: Spectra Logic | ABX3: Spectrum | ABY3: Speed | ABZ3: SPEED LINK | ACA3: Starmatix | ACB3: Star Micronics | ACC3: StarTech | ACD3: SteelSeries | ACE3: ST-Lab | ACF3: StorageTek | ACG3: StorDigital | ACH3: Storix | ACI3: Stormtek | ACJ3: STRONG | ACK3: SUMVISION | ACL3: Sun | ACM3: Sunbeamtech | ACN3: Sunix | ACO3: Sun Microsystems | ACP3: SUNON | ACQ3: Supermicro | ACR3: Super Talent | ACS3: SVP | ACT3: Swann's | ACU3: Sweex | ACV3: Swiftech | ACW3: Swissbit | ACX3: Syba | ACY3: SYLVANIA | ACZ3: Symantec | ADA3: Synology | ADB3: Syntax | ADC3: SyQuest | ADD3: Systemax | ADE3: SySTOR Systems | ADF3: Tadpole | ADG3: Tagan | ADH3: TallyGenicom | ADI3: Tandberg | ADJ3: Targus | ADK3: TASCAM | ADL3: Tatung | ADM3: TAXAN | ADN3: TDK | ADO3: TEAC | ADP3: TechniSat | ADQ3: TechWorks | ADR3: Tecmar | ADS3: Tekram | ADT3: Tektronix | ADU3: Telex | ADV3: Terapin | ADW3: TERRATEC | ADX3: Thermaltake | ADY3: Tiger | ADZ3: Titan | AEA3: Tixi | AEB3: Toshiba | AEC3: Total Micro | AED3: Touch Dynamic | AEE3: Tower | AEF3: TP-LINK | AEG3: Trace | AEH3: Transcend | AEI3: Transonic | AEJ3: Traxdata | AEK3: Trek 2000 International | AEL3: Trend Micro | AEM3: TRENDnet | AEN3: Tritton Technology | AEO3: Triumph | AEP3: True Data | AEQ3: Trust | AER3: Tulip | AES3: Tuniq | AET3: Turtle Beach | AEU3: Twin | AEV3: TwinHan | AEW3: TwinHead | AEX3: TwinMOS | AEY3: TX | AEZ3: TYAN | AFA3: TYCO | AFB3: Typhoon | AFC3: Ubiquiti Networks | AFD3: Ulead | AFE3: Ultima | AFF3: Ultimate Sound | AFG3: Ultimate Technology | AFH3: Ultra | AFI3: Ultramax | AFJ3: UMAX | AFK3: Unisys | AFL3: Unity Digital | AFM3: USRobotics | AFN3: Utmost | AFO3: uxcell | AFP3: V7 | AFQ3: Vantec | AFR3: Veho | AFS3: Verbatim | AFT3: Verifone | AFU3: Veritas | AFV3: Verity Systems | AFW3: VIA | AFX3: Victory | AFY3: Videk | AFZ3: ViewSonic | AGA3: Viking | AGB3: Viking Components | AGC3: Viking InterWorks | AGD3: Vinpower | AGE3: Vision | AGF3: Visioneer | AGG3: VisionTek | AGH3: VistaQuest | AGI3: VistaSource | AGJ3: Vivanco | AGK3: Vivastar | AGL3: Voodoo PC | AGM3: VuPoint | AGN3: Wacom | AGO3: Waitec | AGP3: WANG | AGQ3: WatchGuard | AGR3: Western Digital | AGS3: WIN | AGT3: WinBook | AGU3: Wintergreen | AGV3: Wyse | AGW3: Wytron Technology | AGX3: X-10 | AGY3: X2 | AGZ3: Xandros | AHA3: Xara | AHB3: XBLUE | AHC3: Xerox | AHD3: XFX | AHE3: Xigmatek | AHF3: Ximeta | AHG3: XION | AHH3: Xircom | AHI3: Xitel | AHJ3: X-Micro Technology | AHK3: X-OOM | AHL3: XPS | AHM3: Xystec | AHN3: Yakumo | AHO3: Yamaha | AHP3: Zalman | AHQ3: Zebra | AHR3: Zenith Data Systems | AHS3: ZEROtherm | AHT3: Zerus | AHU3: Zilog | AHV3: Zio Corporation | AHW3: Z Microsystems | AHX3: ZONE | AHY3: Zonet | AHZ3: Zoom | AIA3: ZOTAC | AIB3: ZT Group | AIC3: ZyXEL
A4: 170080 | B4: C:Type | C4: CType | D4: 170080C:Type | E4: REQUIRED | F4: Battery Holder | G4: BIOS Chip | H4: Bridge | I4: Capacitor | J4: CMOS Battery | K4: CPU Bracket | L4: CPU Socket | M4: Expansion Card Slot | N4: Memory Slot | O4: Motherboard Port | P4: Northbridge Chipset | Q4: Peripheral Connector | R4: Power Connector | S4: Southbridge Chipset
A5: 170080 | B5: C:Compatible Motherboard Brand | C5: CCompatibleMotherboardBrand | D5: 170080C:Compatible Motherboard Brand | E5: PREFERRED | F5: For ABIT | G5: For Acer | H5: For AMD | I5: For Arduino | J5: For ASRock | K5: For ASUS | L5: For Biostar | M5: For Dell | N5: For EVGA | O5: For GIGABYTE | P5: For Hercules | Q5: For HP | R5: For IBM | S5: For Intel | T5: For Jetway | U5: For Micro Star | V5: For MSI | W5: For NVIDIA | X5: For Quantum | Y5: For Sapphire | Z5: For SparkFun | AA5: For StarTech | AB5: For VIA | AC5: For Zotac | AD5: Universal
A6: 170080 | B6: C:MPN | C6: CMPN | D6: 170080C:MPN | E6: PREFERRED
A7: 170080 | B7: C:Unit Quantity | C7: CUnitQuantity | D7: 170080C:Unit Quantity | E7: PREFERRED
A8: 170080 | B8: C:Unit Type | C8: CUnitType | D8: 170080C:Unit Type | E8: PREFERRED | F8: Unit | G8: oz | H8: lb | I8: fl oz | J8: gal | K8: ft | L8: ft² | M8: ft³
A9: 170080 | B9: C:Country of Origin | C9: CCountryofOrigin | D9: 170080C:Country of Origin | E9: OPTIONAL | F9: Afghanistan | G9: Albania | H9: Algeria | I9: Andorra | J9: Angola | K9: Anguilla | L9: Antigua and Barbuda | M9: Argentina | N9: Armenia | O9: Aruba | P9: Australia | Q9: Austria | R9: Azerbaijan | S9: Bahamas | T9: Bahrain | U9: Bangladesh | V9: Barbados | W9: Belarus | X9: Belgium | Y9: Belize | Z9: Benin | AA9: Bermuda | AB9: Bhutan | AC9: Bolivia | AD9: Bosnia and Herzegovina | AE9: Botswana | AF9: Brazil | AG9: British Indian Ocean Territory | AH9: British Virgin Islands | AI9: Brunei Darussalam | AJ9: Bulgaria | AK9: Burkina Faso | AL9: Burundi | AM9: Cambodia | AN9: Cameroon | AO9: Canada | AP9: Canary Islands | AQ9: Cape Verde | AR9: Cayman Islands | AS9: Central African Republic | AT9: Chad | AU9: Chile | AV9: China | AW9: Christmas Islands | AX9: Cocos (Keeling) Islands | AY9: Colombia | AZ9: Comoros | BA9: Congo, Republic of the | BB9: Congo, The Democratic Republic of the | BC9: Cook Islands | BD9: Costa Rica | BE9: Côte d'Ivoire | BF9: Croatia | BG9: Cuba | BH9: Curacao | BI9: Cyprus | BJ9: Czech Republic | BK9: Denmark | BL9: Djibouti | BM9: Dominica | BN9: Dominican Republic | BO9: Ecuador | BP9: Egypt | BQ9: El Salvador | BR9: Equatorial Guinea | BS9: Eritrea | BT9: Estonia | BU9: Eswatini | BV9: Ethiopia | BW9: Falkland Islands | BX9: Faroe Islands | BY9: Fiji | BZ9: Finland | CA9: France | CB9: French Guiana | CC9: French Polynesia Includes Tahiti | CD9: French Southern Territories and Antartic Lands | CE9: Gabon | CF9: Gambia | CG9: Gaza Strip | CH9: Georgia | CI9: Germany | CJ9: Ghana | CK9: Gibraltar | CL9: Greece | CM9: Greenland | CN9: Grenada | CO9: Guadeloupe | CP9: Guam | CQ9: Guatemala | CR9: Guernsey | CS9: Guinea | CT9: Guinea-Bissau | CU9: Guyana | CV9: Haiti | CW9: Heard Island and Mcdonald Islands | CX9: Honduras | CY9: Hong Kong | CZ9: Hungary | DA9: Iceland | DB9: India | DC9: Indonesia | DD9: Iran, Islamic Republic of | DE9: Iraq | DF9: Ireland | DG9: Israel | DH9: Italy | DI9: Jamaica | DJ9: Japan | DK9: Jersey | DL9: Jordan | DM9: Kazakhstan | DN9: Kenya | DO9: Kiribati | DP9: Kosovo | DQ9: Kuwait | DR9: Kyrgyzstan | DS9: Lao People's Democratic Republic | DT9: Latvia | DU9: Lebanon | DV9: Lesotho | DW9: Liberia | DX9: Libya | DY9: Liechtenstein | DZ9: Lithuania | EA9: Luxembourg | EB9: Macau | EC9: Madagascar | ED9: Madeira Island | EE9: Malawi | EF9: Malaysia | EG9: Maldives | EH9: Mali | EI9: Malta | EJ9: Marshall Islands | EK9: Martinique | EL9: Mauritania | EM9: Mauritius | EN9: Mayotte | EO9: Mexico | EP9: Micronesia, Federated States of | EQ9: Moldova, Republic of | ER9: Monaco | ES9: Mongolia | ET9: Montenegro | EU9: Montserrat | EV9: Morocco | EW9: Mozambique | EX9: Myanmar / Burma | EY9: Namibia | EZ9: Nauru | FA9: Nepal | FB9: Netherlands | FC9: New Caledonia | FD9: New Zealand | FE9: Nicaragua | FF9: Niger | FG9: Nigeria | FH9: Niue | FI9: Norfolk Island | FJ9: Northern Mariana Islands | FK9: North Korea (Democratic People's Republic of Korea) | FL9: North Macedonia | FM9: Norway | FN9: Oman | FO9: Pakistan | FP9: Palau | FQ9: Panama | FR9: Papua New Guinea | FS9: Paraguay | FT9: Peru | FU9: Philippines | FV9: Poland | FW9: Portugal | FX9: Puerto Rico | FY9: Qatar | FZ9: Reunion | GA9: Romania | GB9: Russian Federation | GC9: Rwanda | GD9: Saint Barthélemy | GE9: Saint Helena | GF9: Saint Kitts and Nevis | GG9: Saint Lucia | GH9: Saint-Martin | GI9: Saint Pierre and Miquelon | GJ9: Saint Vincent and the Grenadines | GK9: Samoa | GL9: San Marino | GM9: Sao Tome and Principe | GN9: Saudi Arabia | GO9: Senegal | GP9: Serbia | GQ9: Seychelles | GR9: Sierra Leone | GS9: Singapore | GT9: Sint Eustatius | GU9: Sint Maarten | GV9: Slovakia | GW9: Slovenia | GX9: Solomon Islands | GY9: Somalia | GZ9: South Africa | HA9: South Georgia and the South Sandwich Islands | HB9: South Korea (Republic of Korea) | HC9: Spain | HD9: Sri Lanka | HE9: Sudan | HF9: Suriname | HG9: Svalbard and Jan Mayen | HH9: Sweden | HI9: Switzerland | HJ9: Syria | HK9: Taiwan | HL9: Tajikistan | HM9: Tanzania, United Republic of | HN9: Thailand | HO9: Togo | HP9: Tokelau | HQ9: Tonga | HR9: Trinidad and Tobago | HS9: Tristan da Cunha | HT9: Tunisia | HU9: Türkiye | HV9: Turkmenistan | HW9: Turks and Caicos Islands | HX9: Tuvalu | HY9: Uganda | HZ9: Ukraine | IA9: United Arab Emirates | IB9: United Kingdom | IC9: United States | ID9: Uruguay | IE9: Uzbekistan | IF9: Vanuatu | IG9: Vatican City | IH9: Venezuela | II9: Vietnam | IJ9: Virgin Islands | IK9: Wallis and Futuna | IL9: West Bank | IM9: Yemen | IN9: Zambia | IO9: Zimbabwe
A10: 170080 | B10: C:California Prop 65 Warning | C10: CCaliforniaProp65Warning | D10: 170080C:California Prop 65 Warning | E10: OPTIONAL
A11: 170080 | B11: C:Item Height | C11: CItemHeight | D11: 170080C:Item Height | E11: OPTIONAL
A12: 170080 | B12: C:Item Length | C12: CItemLength | D12: 170080C:Item Length | E12: OPTIONAL
A13: 170080 | B13: C:Item Width | C13: CItemWidth | D13: 170080C:Item Width | E13: OPTIONAL
A14: 170080 | B14: C:Manufacturer Warranty | C14: CManufacturerWarranty | D14: 170080C:Manufacturer Warranty | E14: OPTIONAL | F14: 10 Years | G14: 1 Month | H14: 1 Year | I14: 2 Years | J14: 3 Months | K14: 3 Years | L14: 4 Years | M14: 5 Years | N14: 6 Months | O14: 9 Months | P14: Lifetime

Sheet ConditionDescriptors
A2: CategoryId | B2: ConditionId | C2: ConditionDescriptorName | D2: FunctionName | E2: CategoryConditionDescriptorCombined | F2: Required | G2: Closed | H2: Values
